sphinx_galleria/__init__.py
sphinx_galleria/collector.py
sphinx_galleria/directive.py
sphinx_galleria/locale/sphinx.pot
sphinx_galleria/locale/fr/LC_MESSAGES/sphinx.mo
sphinx_galleria/locale/fr/LC_MESSAGES/sphinx.po
sphinx_galleria/locale/nl/LC_MESSAGES/sphinx.mo
sphinx_galleria/locale/nl/LC_MESSAGES/sphinx.po
sphinx_galleria/static/sphinxgalleria/sphinxgalleria.css
sphinx_galleria/static/sphinxgalleria/sphinxgalleria.mjs
sphinx_galleria-2.1.0.dist-info/entry_points.txt
sphinx_galleria-2.1.0.dist-info/LICENSE
sphinx_galleria-2.1.0.dist-info/LICENSE-de
sphinx_galleria-2.1.0.dist-info/LICENSE-fr
sphinx_galleria-2.1.0.dist-info/LICENSE-nl
sphinx_galleria-2.1.0.dist-info/WHEEL
sphinx_galleria-2.1.0.dist-info/METADATA
sphinx_galleria-2.1.0.dist-info/RECORD
